LICENSE
README.md
setup.cfg
setup.py
bin/cryptofy
cryptofy/__init__.py
cryptofy.egg-info/PKG-INFO
cryptofy.egg-info/SOURCES.txt
cryptofy.egg-info/dependency_links.txt
cryptofy.egg-info/not-zip-safe
cryptofy.egg-info/requires.txt
cryptofy.egg-info/top_level.txt