Metadata-Version: 2.1
Name: cryptofy
Version: 1.1.0
Summary: Simple encryption/decryption functions for Python
Home-page: https://github.com/homedepot/cryptofy
Author: Mike Phillipson
Author-email: MICHAEL_PHILLIPSON1@homedepot.com
License: Apache 2.0
Platform: UNKNOWN
